smartexporter/__init__.py
smartexporter/smartexporter.py
smartexporter_tspspi-0.0.2.dist-info/LICENSE.md
smartexporter_tspspi-0.0.2.dist-info/METADATA
smartexporter_tspspi-0.0.2.dist-info/WHEEL
smartexporter_tspspi-0.0.2.dist-info/entry_points.txt
smartexporter_tspspi-0.0.2.dist-info/top_level.txt
smartexporter_tspspi-0.0.2.dist-info/RECORD
