Metadata-Version: 2.1
Name: smartexporter-tspspi
Version: 0.0.2
Summary: Simple Python SMART exporter for Prometheus on FreeBSD
Home-page: https://github.com/tspspi/smartexporter
Author: Thomas Spielauer
Author-email: pypipackages01@tspi.at
Classifier: Programming Language :: Python :: 3
Classifier: License :: OSI Approved :: BSD License
Classifier: Operating System :: POSIX :: BSD :: FreeBSD
Requires-Python: >=3.6
License-File: LICENSE.md
Requires-Dist: daemonize (>=2.5.0)
Requires-Dist: lockfile (>=0.12.2)
Requires-Dist: prometheus-client (>=0.13.1)
